igptai/__init__.py
igptai/async_igpt.py
igptai/igpt.py
igptai-1.1.0.dist-info/LICENSE.txt
igptai-1.1.0.dist-info/METADATA
igptai-1.1.0.dist-info/WHEEL
igptai-1.1.0.dist-info/RECORD
