Metadata-Version: 2.1
Name: igptai
Version: 1.1.0
Summary: Official Python SDK for the iGPT API
Home-page: https://www.igpt.ai/
License: MIT
Keywords: igpt,ai,igptai,sdk,api,llm,recall,datasources
Author: iGPT
Author-email: hello@igpt.ai
Requires-Python: >=3.8,<4.0
Classifier: License :: OSI Approved :: MIT License
Classifier: Programming Language :: Python :: 3
Classifier: Programming Language :: Python :: 3.8
Classifier: Programming Language :: Python :: 3.9
Classifier: Programming Language :: Python :: 3.10
Classifier: Programming Language :: Python :: 3.11
Classifier: Programming Language :: Python :: 3.12
Classifier: Programming Language :: Python :: 3.13
Requires-Dist: aiohttp (>=3.9.0,<4.0.0)
Requires-Dist: requests (>=2.31.0,<3.0.0)
Project-URL: Documentation, https://docs.igpt.ai
Project-URL: Repository, https://github.com/igptai/igpt-python
